python_jenkins_monitor/__init__.py
python_jenkins_monitor/python_jenkins_monitor.py
python_jenkins_monitor-1.4.1.dist-info/LICENSE
python_jenkins_monitor-1.4.1.dist-info/METADATA
python_jenkins_monitor-1.4.1.dist-info/WHEEL
python_jenkins_monitor-1.4.1.dist-info/top_level.txt
python_jenkins_monitor-1.4.1.dist-info/RECORD
