Metadata-Version: 2.1
Name: python-jenkins-monitor
Version: 1.4.1
Summary: Simulate Jenkins scheduled task settings,for monitor.
Home-page: https://github.com/Woqurefan
Author: wqrf
Author-email: 1074321997@qq.com
License: MIT
Keywords: monitor,jenkins,python,wqrf
Platform: UNKNOWN
